{
  "resourceType" : "ValueSet",
  "id" : "KMCAppPackages",
  "text" : {
    "status" : "generated",
    "div" : "<div xmlns=\"http://www.w3.org/1999/xhtml\"><p>This value set includes codes based on the following rules:</p><ul><li>Include codes from <a href=\"CodeSystem-kiola-device-kmc-cs.html\"><code>https://fhir.ehealth-systems.at/kiola/device/kmc</code></a> where concept  is-a  <a href=\"CodeSystem-kiola-device-kmc-cs.html#kiola-device-kmc-cs-app_package\">app_package</a></li></ul><p>This value set excludes codes based on the following rules:</p><ul><li>Exclude these codes as defined in <a href=\"CodeSystem-kiola-device-kmc-cs.html\"><code>https://fhir.ehealth-systems.at/kiola/device/kmc</code></a><table class=\"none\"><tr><td style=\"white-space:nowrap\"><b>Code</b></td><td><b>Display</b></td></tr><tr><td><a href=\"CodeSystem-kiola-device-kmc-cs.html#kiola-device-kmc-cs-app_package\">app_package</a></td><td style=\"color: #cccccc\">App package that handles the data transmission from the device</td></tr></table></li></ul></div>"
  },
  "url" : "https://fhir.ehealth-systems.at/artifacts/ValueSet/KMCAppPackages",
  "version" : "0.1.0",
  "name" : "KMCAppPackages",
  "title" : "KMC App Packages",
  "status" : "active",
  "date" : "2024-03-11T08:55:33+00:00",
  "contact" : [{
    "name" : "AIT Austrian Institute of Technology",
    "telecom" : [{
      "system" : "email",
      "value" : "mailto:office@ait.ac.at"
    }]
  }],
  "description" : "App package IDs of first and 3rd party apps, that might be launched by a mobile client to facilitate the transmission process.",
  "compose" : {
    "include" : [{
      "system" : "https://fhir.ehealth-systems.at/kiola/device/kmc",
      "filter" : [{
        "property" : "concept",
        "op" : "is-a",
        "value" : "app_package"
      }]
    }],
    "exclude" : [{
      "system" : "https://fhir.ehealth-systems.at/kiola/device/kmc",
      "concept" : [{
        "code" : "app_package"
      }]
    }]
  }
}