{
  "resourceType" : "ValueSet",
  "id" : "regulatoryEntitlementStatusVs",
  "text" : {
    "status" : "generated",
    "div" : "<div xmlns=\"http://www.w3.org/1999/xhtml\"><ul><li>Include all codes defined in <a href=\"CodeSystem-regulatoryEntitlementStatusCs.html\"><code>https://spor.ema.europa.eu/v1/lists/100000072049</code></a></li></ul></div>"
  },
  "url" : "https://ema.europa.eu/fhir/vs/regulatoryEntitlementStatus",
  "version" : "0.1.0",
  "name" : "RegulatoryEntitlementStatusVs",
  "title" : "The Regulatory Entitlement Status Value Set",
  "status" : "active",
  "date" : "2024-05-23T12:55:33+00:00",
  "publisher" : "AGES",
  "contact" : [{
    "name" : "AGES",
    "telecom" : [{
      "system" : "url",
      "value" : "https://www.ages.at/"
    }]
  }],
  "compose" : {
    "include" : [{
      "system" : "https://spor.ema.europa.eu/v1/lists/100000072049"
    }]
  }
}