<?xml version="1.0" encoding="UTF-8"?>

<Bundle xmlns="http://hl7.org/fhir">
  <id value="06efaccb-f248-4cea-a41b-5cc605291a0c"/>
  <meta>
    <lastUpdated value="2024-10-24T17:45:49.910+00:00"/>
  </meta>
  <type value="collection"/>
  <entry>
    <fullUrl value="http://example.org/ValueSet/moped-WorkflowStatus-valueset"/>
    <resource>
      <ValueSet>
        <text>
          <status value="generated"/>
          <div xmlns="http://www.w3.org/1999/xhtml">
            <p class="res-header-id">
              <b>Generated Narrative: ValueSet </b>
            </p>
            <p>This value set contains 0 concepts</p>
            <table class="codes">
              <tr>
                <td style="white-space:nowrap">
                  <b>Code</b>
                </td>
                <td>
                  <b>System</b>
                </td>
                <td>
                  <b>Display</b>
                </td>
              </tr>
            </table>
          </div>
        </text>
        <url value="http://example.org/ValueSet/moped-WorkflowStatus-valueset"/>
        <version value="0.1.0"/>
        <name value="WorkflowStatus"/>
        <title value="Workflow Status eines Falls"/>
        <status value="draft"/>
        <date value="2024-10-24T17:45:49+00:00"/>
        <expansion>
          <identifier value="urn:uuid:e0ccbf6f-c08d-4587-bb00-f58c0b353ee4"/>
          <timestamp value="2024-10-24T17:46:43+00:00"/>
          <total value="0"/>
          <offset value="0"/>
          <parameter>
            <name value="count"/>
            <valueInteger value="1000"/>
          </parameter>
          <parameter>
            <name value="offset"/>
            <valueInteger value="0"/>
          </parameter>
          <parameter>
            <name value="excludeNested"/>
            <valueBoolean value="false"/>
          </parameter>
        </expansion>
      </ValueSet>
    </resource>
  </entry>
</Bundle>