<?xml version="1.0" encoding="UTF-8"?>

<Bundle xmlns="http://hl7.org/fhir">
  <id value="071794f8-cc9b-496f-a349-b3f95aa6fbf7"/>
  <meta>
    <lastUpdated value="2024-10-11T08:15:28.340+00:00"/>
  </meta>
  <type value="collection"/>
  <entry>
    <fullUrl value="http://example.org/ValueSet/moped-WorkflowStatus-valueset"/>
    <resource>
      <ValueSet>
        <text>
          <status value="generated"/>
          <div xmlns="http://www.w3.org/1999/xhtml">
            <p class="res-header-id">
              <b>Generated Narrative: ValueSet </b>
            </p>
            <p>This value set contains 0 concepts</p>
            <table class="codes">
              <tr>
                <td style="white-space:nowrap">
                  <b>Code</b>
                </td>
                <td>
                  <b>System</b>
                </td>
                <td>
                  <b>Display</b>
                </td>
              </tr>
            </table>
          </div>
        </text>
        <url value="http://example.org/ValueSet/moped-WorkflowStatus-valueset"/>
        <version value="0.1.0"/>
        <name value="WorkflowStatus"/>
        <title value="Workflow Status eines Falls"/>
        <status value="draft"/>
        <date value="2024-10-11T08:15:28+00:00"/>
        <expansion>
          <identifier value="urn:uuid:eff5c689-694e-4df1-9bad-6e32f03187bf"/>
          <timestamp value="2024-10-11T08:16:27+00:00"/>
          <total value="0"/>
          <offset value="0"/>
          <parameter>
            <name value="count"/>
            <valueInteger value="1000"/>
          </parameter>
          <parameter>
            <name value="offset"/>
            <valueInteger value="0"/>
          </parameter>
          <parameter>
            <name value="excludeNested"/>
            <valueBoolean value="false"/>
          </parameter>
        </expansion>
      </ValueSet>
    </resource>
  </entry>
  <entry>
    <fullUrl value="http://example.org/ValueSet/moped-altersgruppe-valueset"/>
    <resource>
      <ValueSet>
        <text>
          <status value="generated"/>
          <div xmlns="http://www.w3.org/1999/xhtml">
            <p class="res-header-id">
              <b>Generated Narrative: ValueSet </b>
            </p>
            <p>This value set contains 0 concepts</p>
            <table class="codes">
              <tr>
                <td style="white-space:nowrap">
                  <b>Code</b>
                </td>
                <td>
                  <b>System</b>
                </td>
                <td>
                  <b>Display</b>
                </td>
              </tr>
            </table>
          </div>
        </text>
        <url value="http://example.org/ValueSet/moped-altersgruppe-valueset"/>
        <version value="0.1.0"/>
        <name value="Altersgruppe"/>
        <title value="Altersgruppe des Patienten"/>
        <status value="draft"/>
        <date value="2024-10-11T08:15:28+00:00"/>
        <expansion>
          <identifier value="urn:uuid:52f22b98-3404-4add-b255-5a9fd9583aae"/>
          <timestamp value="2024-10-11T08:16:27+00:00"/>
          <total value="0"/>
          <offset value="0"/>
          <parameter>
            <name value="count"/>
            <valueInteger value="1000"/>
          </parameter>
          <parameter>
            <name value="offset"/>
            <valueInteger value="0"/>
          </parameter>
          <parameter>
            <name value="excludeNested"/>
            <valueBoolean value="false"/>
          </parameter>
        </expansion>
      </ValueSet>
    </resource>
  </entry>
</Bundle>